LICENSE
MANIFEST.in
README.md
setup.cfg
setup.py
lastfm_cli_scrobbler/__init__.py
lastfm_cli_scrobbler/last_my.py
lastfm_cli_scrobbler/last_pylast.py
lastfm_cli_scrobbler.egg-info/PKG-INFO
lastfm_cli_scrobbler.egg-info/SOURCES.txt
lastfm_cli_scrobbler.egg-info/dependency_links.txt
lastfm_cli_scrobbler.egg-info/entry_points.txt
lastfm_cli_scrobbler.egg-info/requires.txt
lastfm_cli_scrobbler.egg-info/top_level.txt