Metadata-Version: 2.1
Name: lastfm-cli-scrobbler
Version: 0.1.0
Summary: Last.fm CLI Scrobbler
Home-page: https://github.com/maximtrp/lastfm-cli-scrobbler
Author: Maksim Terpilowski
Author-email: maximtrp@gmail.com
License: UNKNOWN
Keywords: python,lastfm,cli,scrobbler
Platform: UNKNOWN
Classifier: Development Status :: 3 - Alpha
Classifier: Intended Audience :: Information Technology
Classifier: Intended Audience :: End Users/Desktop
Classifier: Topic :: Home Automation
Classifier: Topic :: Internet
Classifier: License :: OSI Approved :: BSD License
Classifier: Programming Language :: Python :: 3
Classifier: Programming Language :: Python :: 3.5
Classifier: Programming Language :: Python :: 3.6
Classifier: Programming Language :: Python :: 3.7
Classifier: Programming Language :: Python :: 3.8
Classifier: Programming Language :: Python :: 3.9
Requires-Python: >=3.5
